README.md
setup.py
Extre/__init__.py
Extre/__main__.py
Extre/_wrappers.py
Extre/clientutils.py
Extre/config.py
Extre/connections.py
Extre/core.py
Extre/events.py
Extre/extremecmd.py
Extre/func.py
Extre/googleimages.py
Extre/heroku.py
Extre/process.py
Extre/sudo.py
Extre/utils.py
Extre/var.py
Extre/variables.py
Extre/version.py
Extre.egg-info/PKG-INFO
Extre.egg-info/SOURCES.txt
Extre.egg-info/dependency_links.txt
Extre.egg-info/requires.txt
Extre.egg-info/top_level.txt